<?xml version="1.0" encoding="UTF-8"?>
<!DOCTYPE mapper PUBLIC "-//mybatis.org//DTD Mapper 3.0//EN" "http://mybatis.org/dtd/mybatis-3-mapper.dtd">
<mapper namespace="com.yuanchuangyun.libra.dao.BizTrademarkApplicantRelMapper">
  <resultMap id="BaseResultMap" type="com.yuanchuangyun.libra.model.BizTrademarkApplicantRel">
    <!--
      WARNING - @mbg.generated
      This element is automatically generated by MyBatis Generator, do not modify.
      This element was generated on Wed Oct 19 17:51:59 CST 2016.
    -->
    <id column="ID" jdbcType="VARCHAR" property="id" />
    <result column="TRADEMARK_ID" jdbcType="VARCHAR" property="trademarkId" />
    <result column="APPLICANT_ID" jdbcType="VARCHAR" property="applicantId" />
  </resultMap>
  <sql id="Base_Column_List">
    <!--
      WARNING - @mbg.generated
      This element is automatically generated by MyBatis Generator, do not modify.
      This element was generated on Wed Oct 19 17:51:59 CST 2016.
    -->
    ID, TRADEMARK_ID, APPLICANT_ID
  </sql>
  <select id="selectByPrimaryKey" parameterType="java.lang.String" resultMap="BaseResultMap">
    <!--
      WARNING - @mbg.generated
      This element is automatically generated by MyBatis Generator, do not modify.
      This element was generated on Wed Oct 19 17:51:59 CST 2016.
    -->
    select 
    <include refid="Base_Column_List" />
    from biz_trademark_applicant_rel
    where ID = #{id,jdbcType=VARCHAR}
  </select>
  <delete id="deleteByPrimaryKey" parameterType="java.lang.String">
    <!--
      WARNING - @mbg.generated
      This element is automatically generated by MyBatis Generator, do not modify.
      This element was generated on Wed Oct 19 17:51:59 CST 2016.
    -->
    delete from biz_trademark_applicant_rel
    where ID = #{id,jdbcType=VARCHAR}
  </delete>
  <insert id="insert" parameterType="com.yuanchuangyun.libra.model.BizTrademarkApplicantRel">
    <!--
      WARNING - @mbg.generated
      This element is automatically generated by MyBatis Generator, do not modify.
      This element was generated on Wed Oct 19 17:51:59 CST 2016.
    -->
    insert into biz_trademark_applicant_rel (ID, TRADEMARK_ID, APPLICANT_ID
      )
    values (#{id,jdbcType=VARCHAR}, #{trademarkId,jdbcType=VARCHAR}, #{applicantId,jdbcType=VARCHAR}
      )
  </insert>
  <insert id="insertSelective" parameterType="com.yuanchuangyun.libra.model.BizTrademarkApplicantRel">
    <!--
      WARNING - @mbg.generated
      This element is automatically generated by MyBatis Generator, do not modify.
      This element was generated on Wed Oct 19 17:51:59 CST 2016.
    -->
    insert into biz_trademark_applicant_rel
    <trim prefix="(" suffix=")" suffixOverrides=",">
      <if test="id != null">
        ID,
      </if>
      <if test="trademarkId != null">
        TRADEMARK_ID,
      </if>
      <if test="applicantId != null">
        APPLICANT_ID,
      </if>
    </trim>
    <trim prefix="values (" suffix=")" suffixOverrides=",">
      <if test="id != null">
        #{id,jdbcType=VARCHAR},
      </if>
      <if test="trademarkId != null">
        #{trademarkId,jdbcType=VARCHAR},
      </if>
      <if test="applicantId != null">
        #{applicantId,jdbcType=VARCHAR},
      </if>
    </trim>
  </insert>
  <update id="updateByPrimaryKeySelective" parameterType="com.yuanchuangyun.libra.model.BizTrademarkApplicantRel">
    <!--
      WARNING - @mbg.generated
      This element is automatically generated by MyBatis Generator, do not modify.
      This element was generated on Wed Oct 19 17:51:59 CST 2016.
    -->
    update biz_trademark_applicant_rel
    <set>
      <if test="trademarkId != null">
        TRADEMARK_ID = #{trademarkId,jdbcType=VARCHAR},
      </if>
      <if test="applicantId != null">
        APPLICANT_ID = #{applicantId,jdbcType=VARCHAR},
      </if>
    </set>
    where ID = #{id,jdbcType=VARCHAR}
  </update>
  <update id="updateByPrimaryKey" parameterType="com.yuanchuangyun.libra.model.BizTrademarkApplicantRel">
    <!--
      WARNING - @mbg.generated
      This element is automatically generated by MyBatis Generator, do not modify.
      This element was generated on Wed Oct 19 17:51:59 CST 2016.
    -->
    update biz_trademark_applicant_rel
    set TRADEMARK_ID = #{trademarkId,jdbcType=VARCHAR},
      APPLICANT_ID = #{applicantId,jdbcType=VARCHAR}
    where ID = #{id,jdbcType=VARCHAR}
  </update>
</mapper>